{
	"db_type" : "local",
	"db_name" : "Base",
	"data" : [
		{
			"type" : "folder",
			"id" : "Fonts",
			"contents" : [

			]
		},
		{
			"type" : "folder",
			"id" : "Maps",
			"contents" : [
				{
					"type" : "map",
					"id" : "TestMap",
					"source" : "test.png"
				}
			]
		},
		{
			"type" : "folder",
			"id" : "Models",
			"contents" : [
				{
					"type" : "model",
					"id" : "Greek",
					"source" : "greek.obj",
					"material" : {
						"Ka" : [1.0, 1.0, 1.0],
						"Kd" : [1.0, 1.0, 1.0],
						"Ks" : [0.0, 0.0, 0.0],
						"Kd_tex" : "greek.jpg"
					}
				}
			]
		},
		{
			"type" : "folder",
			"id" : "Shaders",
			"contents" : [],
			"__" : [
				{
					"type" : "shader",
					"id" : "Simple"
				}
			]
		}
	]
}